simple_data_collector/__init__.py
simple_data_collector/data_collector.py
simple_data_collector/search_data_converter.py
tests/__init__.py
tests/_search_space_list.py
tests/_test_utils.py
tests/test_append.py
tests/test_callbacks.py
tests/test_compatibility.py
tests/test_parallel.py
tests/test_remove.py
tests/test_save.py
simple_data_collector-0.2.0.dist-info/LICENSE
simple_data_collector-0.2.0.dist-info/METADATA
simple_data_collector-0.2.0.dist-info/WHEEL
simple_data_collector-0.2.0.dist-info/top_level.txt
simple_data_collector-0.2.0.dist-info/RECORD
