Metadata-Version: 2.1
Name: simple-data-collector
Version: 0.2.0
Summary: Thread safe and atomic data collection into csv-files
Home-page: https://github.com/SimonBlanke/data-collector
Author: Simon Blanke
Author-email: simon.blanke@yahoo.com
License: MIT
Keywords: data-science
Platform: UNKNOWN
Classifier: Programming Language :: Python :: 3
Classifier: Programming Language :: Python :: 3.5
Classifier: Programming Language :: Python :: 3.6
Classifier: Programming Language :: Python :: 3.7
Classifier: License :: OSI Approved :: MIT License
Classifier: Operating System :: OS Independent
Classifier: Topic :: Scientific/Engineering :: Information Analysis
Classifier: Topic :: Scientific/Engineering :: Mathematics
Classifier: Topic :: Software Development :: Libraries :: Python Modules
Classifier: Intended Audience :: Developers
Classifier: Intended Audience :: Information Technology
Classifier: Intended Audience :: Science/Research
License-File: LICENSE
Requires-Dist: numpy
Requires-Dist: pandas
Requires-Dist: filelock
